ALU_dir/defs.v
`define IDLE 3'b000
`define FETCHA 3'b001
`define FETCHB 3'b010
`define EXECA 3'b011
`define EXECB 3'b100

`define ADD 5'b00000
`define SUB 5'b00001
`define MUL 5'b00010
`define SHL 5'b00011
`define SHR 5'b00100
`define BAND 5'b00101
`define BOR 5'b00110
`define BXOR 5'b00111
`define AND 5'b01000
`define OR 5'b01001
`define EQ 5'b01010
`define NE 5'b01011
`define GE 5'b01100
`define LE 5'b01101
`define GT 5'b01110
`define LT 5'b01111
`define NEG 5'b10000
`define BNOT 5'b10001
`define NOT 5'b10010

counter_dir/counter.v
module counter(clk,reset,load,inc,d,q);

parameter N = 16;

input clk,reset,load,inc;
input [N-1:0] d;
output [N-1:0] q;
reg [N-1:0] q;

always @(posedge clk or negedge reset)
	// when reset = 0, do reset.
	if(!reset) q <= 0;
	else if(load) q <= d;
	else if(inc) q <= q+1;
endmodule

tinycpu_dir/ram.v
module ram(clk,load,addr,d,q);
parameter DWIDTH = 16,AWIDTH = 12, WORDS = 4096;

input clk,load;
input [AWIDTH-1:0] addr;
input [DWIDTH-1:0] d;
output [DWIDTH-1:0] q;
reg [DWIDTH-1:0] q;
reg [DWIDTH-1:0] mem [WORDS-1:0];

always @(posedge clk)
	begin
		if(load) mem[addr] <= d;
		q <= mem[addr];
	end

integer i;
initial begin
	for(i=0;i<WORDS;i=i+1)
		mem[i] = 0;
/*
mem[12'h000] = 16'hD000;
mem[12'h001] = 16'h3010;
mem[12'h002] = 16'h2010;
mem[12'h003] = 16'hE000;
mem[12'h004] = 16'h2010;
mem[12'h005] = 16'h500F;
mem[12'h006] = 16'h2010;
mem[12'h007] = 16'h1001;
mem[12'h008] = 16'hF001;
mem[12'h009] = 16'h3010;
mem[12'h00A] = 16'hD000;
mem[12'h00B] = 16'h1005;
mem[12'h00C] = 16'hF001;
mem[12'h00D] = 16'hE000;
mem[12'h00E] = 16'h4002;
mem[12'h00F] = 16'h0000;
mem[12'h010] = 16'h0000;
*/

// subtract program
mem[12'h000] = 16'hD000;	//IN
mem[12'h001] = 16'h2005;	//PUSH cnst
mem[12'h002] = 16'hF001;	//SUB
mem[12'h003] = 16'hE000;	//OUT
mem[12'h004] = 16'h0000;	//HALT
mem[12'h005] = 16'h0003;	//cnst: 3

end
endmodule

tinycpu_dir/alu.v
`include "defs.v"

module alu(a,b,f,s);

input [15:0] a,b;
input [4:0] f;
output [15:0] s;
reg [15:0] s;
wire [15:0] x,y;

assign x = a+16'h8000;
assign y = b+16'h8000;

always @(a or b or x or y or f)
	case(f)
		`ADD : s = b+a;
		`SUB : s = b-a;
		`MUL : s =b*a;
		`SHL : s = b<<a;
		`SHR : s = b>>a;
		`BAND : s = b&a;
		`BOR : s = b|a;
		`BXOR : s = b^a;
		`AND : s = b&&a;
		`OR : s = b||a;
		`EQ : s = b==a;
		`NE : s = b!=a;
		`GE : s = y>=x;
		`LE : s = y<=x;
		`GT : s = y>x;
		`LT : s = y<x;
		`NEG : s = -a;
		`BNOT : s = ~a;
		`NOT : s = !a;
		default : s = 16'hxxxx;
	endcase
endmodule

stack_dir/stack.v
module stack(clk,reset,load,push,pop,d,qtop,qnext);
parameter N=8;

input clk,reset,load,push,pop;
input [15:0] d;
output [15:0] qtop,qnext;
reg [15:0] q [N-1:0];

assign qtop = q[0];
assign qnext = q[1];

always @(posedge clk or negedge reset)
	if(!reset) q[0] <= 0;
	else if(load) q[0] <= d;
	else if(pop) q[0] <= q[1];

integer i;
always @(posedge clk or negedge reset)
	for(i=1;i<N-1;i=i+1)
		if(!reset) q[i] <= 0;
		else if(push) q[i] <= q[i-1];
		else if(pop) q[i] <= q[i+1];

always @(posedge clk or negedge reset)
	if(!reset) q[N-1] <= 0;
	else if(push) q[N-1] <= q[N-2];

endmodule

tinycpu_dir/state.v
`include "defs.v"

module state(clk,reset,run,cont,halt,cs);

input clk,reset,run,cont,halt;
output [2:0] cs;
reg [2:0] cs;

always @(posedge clk or negedge reset)
	if(!reset) cs <= `IDLE;
	else
		case(cs)
			`IDLE: if(run) cs <= `FETCHA;
			`FETCHA: cs <= `FETCHB;
			`FETCHB: cs <= `EXECA;
			`EXECA: if(halt) cs <= `IDLE;
					else if(cont) cs <= `EXECB;
					else cs <= `FETCHA;
			
			`EXECB: cs <= `FETCHA;
			default: cs <= 3'bxxx;
		endcase
endmodule

tinycpu_dir/tinycpu.v
`include "defs.v"

module tinycpu(clk,reset,run,in,cs,pcout,irout,qtop,abus,dbus,out);

input clk,reset,run;
input [15:0] in;
output [2:0] cs;
output [15:0] irout,qtop,dbus,out;
output [11:0] pcout,abus;
wire [15:0] qnext,ramout,aluout;

reg [11:0] abus;
reg halt,cont,pcinc,push,pop,abus2pc,dbus2ir,dbus2qtop,
	dbus2ram,dbus2obuf,pc2abus,ir2abus,ir2dbus,
	qtop2dbus,alu2dbus,ram2dbus,in2dbus;
	
counter #(12) pc0(.clk(clk), .reset(reset), .load(abus2pc),
				.inc(pcinc), .d(dbus), .q(pcout));

counter #(16) ir0(.clk(clk), .reset(reset), .load(dbus2ir),
				.inc(0), .d(dbus), .q(irout));

state state0(.clk(clk), .reset(reset), .run(run), .cont(cont),
			.halt(halt), .cs(cs));

stack stack0(.clk(clk), .reset(reset), .load(dbus2qtop),
			.push(push), .pop(pop), .d(dbus), .qtop(qtop),
			.qnext(qnext));

alu alu0(.a(qtop), .b(qnext), .f(irout[4:0]), .s(aluout));

ram #(16,12,4096) ram0(.clk(clk), .load(dbus2ram),
					.addr(abus[11:0]), .d(dbus), .q(ramout));

counter #(16) obuf0(.clk(clk), .reset(reset),
				.load(dbus2obuf), .inc(0), .d(dbus), .q(out));

always @(pc2abus or ir2abus or pcout or irout)
	if(pc2abus) abus <= pcout;
	else if(ir2abus) abus <= irout[11:0];
	else abus <= 12'hxxx;

assign dbus = ir2dbus ? {{4{irout[11]}},irout[11:0]}:16'hzzzz;
assign dbus = qtop2dbus ? qtop:16'hzzzz;
assign dbus = alu2dbus ? aluout:16'hzzzz;
assign dbus = ram2dbus ? ramout:16'hzzzz;
assign dbus = in2dbus ? in:16'hzzzz;

always @(cs or irout or qtop)
	begin
		halt = 0;pcinc = 0;push = 0;pop = 0;cont = 0;abus2pc = 0;
		dbus2ir = 0;dbus2qtop = 0;dbus2ram = 0;
		dbus2obuf = 0;pc2abus = 0;ir2abus = 0;ir2dbus = 0;
		qtop2dbus = 0;alu2dbus = 0;ram2dbus = 0;in2dbus = 0;
	
	if(cs==`FETCHA)
		begin
			pcinc = 1;pc2abus = 1;
		end
	else if(cs==`FETCHB)
		begin
			ram2dbus = 1;dbus2ir = 1;
		end
	
	else if(cs==`EXECA)
		case(irout[15:12])
			`PUSHI:
				begin
					ir2dbus = 1;dbus2qtop = 1;push = 1;
				end
			
			`PUSH:
				begin
					ir2abus = 1;cont = 1;
				end
				
			`POP:
				begin
					ir2abus = 1;qtop2dbus = 1;dbus2ram = 1;pop = 1;
				end
			
			`JMP:
				begin
					ir2abus = 1;abus2pc = 1;
				end
			
			`JZ:
				begin
					if(qtop==0)
						begin
							ir2abus = 1;abus2pc = 1;
						end
					pop = 1;
				end
			
			`JNZ:
				begin
					if(qtop != 0)
						begin
							ir2abus = 1;abus2pc = 1;
						end
					pop = 1;
				end
			
			`IN:
				begin
					in2dbus = 1;dbus2qtop = 1;push = 1;
				end
			
			`OUT:
				begin
					qtop2dbus = 1;dbus2obuf = 1;pop = 1;
				end
			
			`OP:
				begin
					alu2dbus = 1;dbus2qtop = 1;
					if(irout[4]==0) pop = 1;
				end
			
			default:
				halt = 1;
			endcase
		
		else if(cs==`EXECB)
			if(irout[15:12]==`PUSH)
				begin
					ram2dbus = 1;dbus2qtop = 1;push = 1;
				end
		end
endmodule

tinycpu_dir/tinycpu_subtract_tb.v
`timescale 1ns/1ps
module tinycpu_subtract_tb;

reg clk,reset,run;
reg [15:0] in;
wire [2:0] cs;
wire [15:0] irout,qtop,dbus,out;
wire [11:0] pcout,abus;

tinycpu tinycpu0(.clk(clk), .reset(reset), .run(run), .in(in),
				.cs(cs), .pcout(pcout), .irout(irout), .qtop(qtop),
				.abus(abus), .dbus(dbus), .out(out));

initial begin
	clk = 0;
	forever #50 clk = ~clk;
end

initial begin
	$dumpfile("test.vcd");
	$dumpvars(0,tinycpu_subtract_tb);
	reset = 0;run = 0;in = 3;
	#100 reset = 1;run = 1;
	#100 run = 0;in = 7;
	#12000 $finish;
end
endmodule

tinycpu_dir/test.vcd
$date
	Thu Jul 04 19:04:48 2019
$end
$version
	Icarus Verilog
$end
$timescale
	1ps
$end
$scope module tinycpu_subtract_tb $end
$var wire 16 ! dbus [15:0] $end
$var wire 16 " qtop [15:0] $end
$var wire 12 # pcout [11:0] $end
$var wire 16 $ out [15:0] $end
$var wire 16 % irout [15:0] $end
$var wire 3 & cs [2:0] $end
$var wire 12 ' abus [11:0] $end
$var reg 1 ( clk $end
$var reg 16 ) in [15:0] $end
$var reg 1 * reset $end
$var reg 1 + run $end
$scope module tinycpu0 $end
$var wire 1 ( clk $end
$var wire 16 , dbus [15:0] $end
$var wire 16 - in [15:0] $end
$var wire 16 . qnext [15:0] $end
$var wire 16 / qtop [15:0] $end
$var wire 1 * reset $end
$var wire 1 + run $end
$var wire 16 0 ramout [15:0] $end
$var wire 12 1 pcout [11:0] $end
$var wire 16 2 out [15:0] $end
$var wire 16 3 irout [15:0] $end
$var wire 3 4 cs [2:0] $end
$var wire 16 5 aluout [15:0] $end
$var reg 12 6 abus [11:0] $end
$var reg 1 7 abus2pc $end
$var reg 1 8 alu2dbus $end
$var reg 1 9 cont $end
$var reg 1 : dbus2ir $end
$var reg 1 ; dbus2obuf $end
$var reg 1 < dbus2qtop $end
$var reg 1 = dbus2ram $end
$var reg 1 > halt $end
$var reg 1 ? in2dbus $end
$var reg 1 @ ir2abus $end
$var reg 1 A ir2dbus $end
$var reg 1 B pc2abus $end
$var reg 1 C pcinc $end
$var reg 1 D pop $end
$var reg 1 E push $end
$var reg 1 F qtop2dbus $end
$var reg 1 G ram2dbus $end
$scope module alu0 $end
$var wire 16 H a [15:0] $end
$var wire 16 I b [15:0] $end
$var wire 5 J f [4:0] $end
$var wire 16 K y [15:0] $end
$var wire 16 L x [15:0] $end
$var reg 16 M s [15:0] $end
$upscope $end
$scope module ir0 $end
$var wire 1 ( clk $end
$var wire 16 N d [15:0] $end
$var wire 1 O inc $end
$var wire 1 : load $end
$var wire 1 * reset $end
$var reg 16 P q [15:0] $end
$upscope $end
$scope module obuf0 $end
$var wire 1 ( clk $end
$var wire 16 Q d [15:0] $end
$var wire 1 R inc $end
$var wire 1 ; load $end
$var wire 1 * reset $end
$var reg 16 S q [15:0] $end
$upscope $end
$scope module pc0 $end
$var wire 1 ( clk $end
$var wire 12 T d [11:0] $end
$var wire 1 C inc $end
$var wire 1 7 load $end
$var wire 1 * reset $end
$var reg 12 U q [11:0] $end
$upscope $end
$scope module ram0 $end
$var wire 12 V addr [11:0] $end
$var wire 1 ( clk $end
$var wire 16 W d [15:0] $end
$var wire 1 = load $end
$var reg 16 X q [15:0] $end
$var integer 32 Y i [31:0] $end
$upscope $end
$scope module stack0 $end
$var wire 1 ( clk $end
$var wire 16 Z d [15:0] $end
$var wire 1 < load $end
$var wire 1 D pop $end
$var wire 1 E push $end
$var wire 16 [ qnext [15:0] $end
$var wire 16 \ qtop [15:0] $end
$var wire 1 * reset $end
$var integer 32 ] i [31:0] $end
$upscope $end
$scope module state0 $end
$var wire 1 ( clk $end
$var wire 1 9 cont $end
$var wire 1 > halt $end
$var wire 1 * reset $end
$var wire 1 + run $end
$var reg 3 ^ cs [2:0] $end
$upscope $end
$upscope $end
$upscope $end
$enddefinitions $end
#0
$dumpvars
b0 ^
b111 ]
b0 \
b0 [
bz Z
b1000000000000 Y
bx X
bz W
bx V
b0 U
bz T
b0 S
0R
bz Q
b0 P
0O
bz N
b0 M
b1000000000000000 L
b1000000000000000 K
b0 J
b0 I
b0 H
0G
0F
0E
0D
0C
0B
0A
0@
0?
0>
0=
0<
0;
0:
09
08
07
bx 6
b0 5
b0 4
b0 3
b0 2
b0 1
bx 0
b0 /
b0 .
b11 -
bz ,
0+
0*
b11 )
0(
bx '
b0 &
b0 %
b0 $
b0 #
b0 "
bz !
$end
#50000
b111 ]
1(
#100000
0(
1+
1*
#150000
b0 '
b0 6
b0 V
1B
1C
b1 &
b1 4
b1 ^
b111 ]
1(
#200000
0(
b111 )
b111 -
0+
#250000
bx '
bx 6
bx V
b0 T
b1101000000000000 !
b1101000000000000 ,
b1101000000000000 N
b1101000000000000 Q
b1101000000000000 W
b1101000000000000 Z
1:
1G
0B
0C
b10 &
b10 4
b10 ^
b1 #
b1 1
b1 U
b1101000000000000 0
b1101000000000000 X
b111 ]
1(
#300000
0(
#350000
b111 T
1E
1<
1?
0G
0:
b111 !
b111 ,
b111 N
b111 Q
b111 W
b111 Z
b1101000000000000 %
b1101000000000000 3
b1101000000000000 P
b11 &
b11 4
b11 ^
bx 0
bx X
b111 ]
1(
#400000
0(
#450000
b1 '
b1 6
b1 V
bz T
bz !
bz ,
bz N
bz Q
bz W
bz Z
b111 5
b111 M
1B
1C
0?
0<
0E
b1000000000000111 L
b111 "
b111 /
b111 H
b111 \
b1 &
b1 4
b1 ^
b111 ]
1(
#500000
0(
#550000
bx '
bx 6
bx V
b101 T
b10000000000101 !
b10000000000101 ,
b10000000000101 N
b10000000000101 Q
b10000000000101 W
b10000000000101 Z
1:
1G
0B
0C
b10 #
b10 1
b10 U
b10 &
b10 4
b10 ^
b10000000000101 0
b10000000000101 X
b111 ]
1(
#600000
0(
#650000
b101 '
b101 6
b101 V
b0 5
b0 M
bz T
b101 J
19
1@
0G
0:
bz !
bz ,
bz N
bz Q
bz W
bz Z
b11 &
b11 4
b11 ^
b10000000000101 %
b10000000000101 3
b10000000000101 P
bx 0
bx X
b111 ]
1(
#700000
0(
#750000
bx '
bx 6
bx V
b11 T
b11 !
b11 ,
b11 N
b11 Q
b11 W
b11 Z
1E
1<
1G
0@
09
b100 &
b100 4
b100 ^
b11 0
b11 X
b111 ]
1(
#800000
0(
#850000
b10 '
b10 6
b10 V
bz T
b11 5
b11 M
1B
1C
0G
0<
0E
bz !
bz ,
bz N
bz Q
bz W
bz Z
b1000000000000111 K
b111 .
b111 I
b111 [
b1000000000000011 L
b11 "
b11 /
b11 H
b11 \
b1 &
b1 4
b1 ^
bx 0
bx X
b111 ]
1(
#900000
0(
#950000
bx '
bx 6
bx V
b1 T
b1111000000000001 !
b1111000000000001 ,
b1111000000000001 N
b1111000000000001 Q
b1111000000000001 W
b1111000000000001 Z
1:
1G
0B
0C
b11 #
b11 1
b11 U
b10 &
b10 4
b10 ^
b1111000000000001 0
b1111000000000001 X
b111 ]
1(
#1000000
0(
#1050000
b100 5
b100 M
b100 T
b1 J
1D
1<
18
0G
0:
b100 !
b100 ,
b100 N
b100 Q
b100 W
b100 Z
b11 &
b11 4
b11 ^
b1111000000000001 %
b1111000000000001 3
b1111000000000001 P
bx 0
bx X
b111 ]
1(
#1100000
0(
#1150000
b11 '
b11 6
b11 V
bz T
bz !
bz ,
bz N
bz Q
bz W
bz Z
1B
1C
08
0<
0D
b1111111111111100 5
b1111111111111100 M
b1 &
b1 4
b1 ^
b1000000000000100 L
b100 "
b100 /
b100 H
b100 \
b1000000000000000 K
b0 .
b0 I
b0 [
b111 ]
1(
#1200000
0(
#1250000
bx '
bx 6
bx V
b0 T
b1110000000000000 !
b1110000000000000 ,
b1110000000000000 N
b1110000000000000 Q
b1110000000000000 W
b1110000000000000 Z
1:
1G
0B
0C
b10 &
b10 4
b10 ^
b100 #
b100 1
b100 U
b1110000000000000 0
b1110000000000000 X
b111 ]
1(
#1300000
0(
#1350000
b100 5
b100 M
b100 T
b0 J
1D
1;
1F
0G
0:
b100 !
b100 ,
b100 N
b100 Q
b100 W
b100 Z
b1110000000000000 %
b1110000000000000 3
b1110000000000000 P
b11 &
b11 4
b11 ^
bx 0
bx X
b111 ]
1(
#1400000
0(
#1450000
b100 '
b100 6
b100 V
bz T
bz !
bz ,
bz N
bz Q
bz W
bz Z
b0 5
b0 M
1B
1C
0F
0;
0D
b100 $
b100 2
b100 S
b1000000000000000 L
b0 "
b0 /
b0 H
b0 \
b1 &
b1 4
b1 ^
b111 ]
1(
#1500000
0(
#1550000
bx '
bx 6
bx V
b0 T
b0 !
b0 ,
b0 N
b0 Q
b0 W
b0 Z
1:
1G
0B
0C
b101 #
b101 1
b101 U
b10 &
b10 4
b10 ^
b0 0
b0 X
b111 ]
1(
#1600000
0(
#1650000
bz T
1>
0G
0:
bz !
bz ,
bz N
bz Q
bz W
bz Z
b11 &
b11 4
b11 ^
b0 %
b0 3
b0 P
bx 0
bx X
b111 ]
1(
#1700000
0(
#1750000
0>
b0 &
b0 4
b0 ^
b111 ]
1(
#1800000
0(
#1850000
b111 ]
1(
#1900000
0(
#1950000
b111 ]
1(
#2000000
0(
#2050000
b111 ]
1(
#2100000
0(
#2150000
b111 ]
1(
#2200000
0(
#2250000
b111 ]
1(
#2300000
0(
#2350000
b111 ]
1(
#2400000
0(
#2450000
b111 ]
1(
#2500000
0(
#2550000
b111 ]
1(
#2600000
0(
#2650000
b111 ]
1(
#2700000
0(
#2750000
b111 ]
1(
#2800000
0(
#2850000
b111 ]
1(
#2900000
0(
#2950000
b111 ]
1(
#3000000
0(
#3050000
b111 ]
1(
#3100000
0(
#3150000
b111 ]
1(
#3200000
0(
#3250000
b111 ]
1(
#3300000
0(
#3350000
b111 ]
1(
#3400000
0(
#3450000
b111 ]
1(
#3500000
0(
#3550000
b111 ]
1(
#3600000
0(
#3650000
b111 ]
1(
#3700000
0(
#3750000
b111 ]
1(
#3800000
0(
#3850000
b111 ]
1(
#3900000
0(
#3950000
b111 ]
1(
#4000000
0(
#4050000
b111 ]
1(
#4100000
0(
#4150000
b111 ]
1(
#4200000
0(
#4250000
b111 ]
1(
#4300000
0(
#4350000
b111 ]
1(
#4400000
0(
#4450000
b111 ]
1(
#4500000
0(
#4550000
b111 ]
1(
#4600000
0(
#4650000
b111 ]
1(
#4700000
0(
#4750000
b111 ]
1(
#4800000
0(
#4850000
b111 ]
1(
#4900000
0(
#4950000
b111 ]
1(
#5000000
0(
#5050000
b111 ]
1(
#5100000
0(
#5150000
b111 ]
1(
#5200000
0(
#5250000
b111 ]
1(
#5300000
0(
#5350000
b111 ]
1(
#5400000
0(
#5450000
b111 ]
1(
#5500000
0(
#5550000
b111 ]
1(
#5600000
0(
#5650000
b111 ]
1(
#5700000
0(
#5750000
b111 ]
1(
#5800000
0(
#5850000
b111 ]
1(
#5900000
0(
#5950000
b111 ]
1(
#6000000
0(
#6050000
b111 ]
1(
#6100000
0(
#6150000
b111 ]
1(
#6200000
0(
#6250000
b111 ]
1(
#6300000
0(
#6350000
b111 ]
1(
#6400000
0(
#6450000
b111 ]
1(
#6500000
0(
#6550000
b111 ]
1(
#6600000
0(
#6650000
b111 ]
1(
#6700000
0(
#6750000
b111 ]
1(
#6800000
0(
#6850000
b111 ]
1(
#6900000
0(
#6950000
b111 ]
1(
#7000000
0(
#7050000
b111 ]
1(
#7100000
0(
#7150000
b111 ]
1(
#7200000
0(
#7250000
b111 ]
1(
#7300000
0(
#7350000
b111 ]
1(
#7400000
0(
#7450000
b111 ]
1(
#7500000
0(
#7550000
b111 ]
1(
#7600000
0(
#7650000
b111 ]
1(
#7700000
0(
#7750000
b111 ]
1(
#7800000
0(
#7850000
b111 ]
1(
#7900000
0(
#7950000
b111 ]
1(
#8000000
0(
#8050000
b111 ]
1(
#8100000
0(
#8150000
b111 ]
1(
#8200000
0(
#8250000
b111 ]
1(
#8300000
0(
#8350000
b111 ]
1(
#8400000
0(
#8450000
b111 ]
1(
#8500000
0(
#8550000
b111 ]
1(
#8600000
0(
#8650000
b111 ]
1(
#8700000
0(
#8750000
b111 ]
1(
#8800000
0(
#8850000
b111 ]
1(
#8900000
0(
#8950000
b111 ]
1(
#9000000
0(
#9050000
b111 ]
1(
#9100000
0(
#9150000
b111 ]
1(
#9200000
0(
#9250000
b111 ]
1(
#9300000
0(
#9350000
b111 ]
1(
#9400000
0(
#9450000
b111 ]
1(
#9500000
0(
#9550000
b111 ]
1(
#9600000
0(
#9650000
b111 ]
1(
#9700000
0(
#9750000
b111 ]
1(
#9800000
0(
#9850000
b111 ]
1(
#9900000
0(
#9950000
b111 ]
1(
#10000000
0(
#10050000
b111 ]
1(
#10100000
0(
#10150000
b111 ]
1(
#10200000
0(
#10250000
b111 ]
1(
#10300000
0(
#10350000
b111 ]
1(
#10400000
0(
#10450000
b111 ]
1(
#10500000
0(
#10550000
b111 ]
1(
#10600000
0(
#10650000
b111 ]
1(
#10700000
0(
#10750000
b111 ]
1(
#10800000
0(
#10850000
b111 ]
1(
#10900000
0(
#10950000
b111 ]
1(
#11000000
0(
#11050000
b111 ]
1(
#11100000
0(
#11150000
b111 ]
1(
#11200000
0(
#11250000
b111 ]
1(
#11300000
0(
#11350000
b111 ]
1(
#11400000
0(
#11450000
b111 ]
1(
#11500000
0(
#11550000
b111 ]
1(
#11600000
0(
#11650000
b111 ]
1(
#11700000
0(
#11750000
b111 ]
1(
#11800000
0(
#11850000
b111 ]
1(
#11900000
0(
#11950000
b111 ]
1(
#12000000
0(
#12050000
b111 ]
1(
#12100000
0(
#12150000
b111 ]
1(
